nise/__init__.py
nise/__main__.py
nise/copy_to_local_dir.py
nise/extract.py
nise/helpers.py
nise/manifest.py
nise/report.py
nise/upload.py
nise/yaml_gen.py
nise/generators/__init__.py
nise/generators/generator.py
nise/generators/aws/__init__.py
nise/generators/aws/aws_constants.py
nise/generators/aws/aws_generator.py
nise/generators/aws/data_transfer_generator.py
nise/generators/aws/ebs_generator.py
nise/generators/aws/ec2_generator.py
nise/generators/aws/marketplace_generator.py
nise/generators/aws/rds_generator.py
nise/generators/aws/route53_generator.py
nise/generators/aws/s3_generator.py
nise/generators/aws/vpc_generator.py
nise/generators/azure/__init__.py
nise/generators/azure/azure_generator.py
nise/generators/azure/bandwidth_generator.py
nise/generators/azure/ccsp_generator.py
nise/generators/azure/data_transfer_generator.py
nise/generators/azure/managed_disk_generator.py
nise/generators/azure/sql_database_generator.py
nise/generators/azure/storage_generator.py
nise/generators/azure/virtual_machine_generator.py
nise/generators/azure/virtual_network_generator.py
nise/generators/gcp/__init__.py
nise/generators/gcp/cloud_storage_generator.py
nise/generators/gcp/compute_engine_generator.py
nise/generators/gcp/disk_generator.py
nise/generators/gcp/gcp_database_generator.py
nise/generators/gcp/gcp_generator.py
nise/generators/gcp/gcp_network_generator.py
nise/generators/gcp/hcs_generator.py
nise/generators/gcp/project_generator.py
nise/generators/ocp/__init__.py
nise/generators/ocp/ocp_generator.py
nise/util/__init__.py
nise/util/constants.py
nise/util/log.py
nise/yaml_generators/__init__.py
nise/yaml_generators/generator.py
nise/yaml_generators/utils.py
nise/yaml_generators/aws/__init__.py
nise/yaml_generators/aws/ec2_instance_types.py
nise/yaml_generators/aws/generator.py
nise/yaml_generators/aws/rds_instance_types.py
nise/yaml_generators/aws/regions.py
nise/yaml_generators/azure/__init__.py
nise/yaml_generators/azure/generator.py
koku_nise-5.3.4.dist-info/METADATA
koku_nise-5.3.4.dist-info/WHEEL
koku_nise-5.3.4.dist-info/entry_points.txt
koku_nise-5.3.4.dist-info/licenses/LICENSE
koku_nise-5.3.4.dist-info/RECORD
