Metadata-Version: 2.4
Name: koku-nise
Version: 5.3.4
Summary: A tool for generating sample cost and usage data for testing purposes.
Maintainer-email: Project Koku <cost_mgmt@redhat.com>
License-File: LICENSE
Classifier: License :: OSI Approved :: GNU Affero General Public License v3
Classifier: Operating System :: OS Independent
Classifier: Programming Language :: Python :: 3
Requires-Python: >=3.11
Requires-Dist: azure-storage-blob>=12.1
Requires-Dist: boto3>=1.11
Requires-Dist: faker>=3.0
Requires-Dist: google-cloud-bigquery>=2.2.0
Requires-Dist: google-cloud-storage>=1.19
Requires-Dist: jinja2>=2.10
Requires-Dist: pyyaml>=5.3
Requires-Dist: requests>=2.22
